bridgebot/__init__.py
bridgebot/action.py
bridgebot/agent.py
bridgebot/dataencoder.py
bridgebot/env.py
bridgebot/exception.py
bridgebot/observation.py
bridgebot/util.py
bridgebot-0.0.3.dist-info/LICENSE
bridgebot-0.0.3.dist-info/METADATA
bridgebot-0.0.3.dist-info/WHEEL
bridgebot-0.0.3.dist-info/top_level.txt
bridgebot-0.0.3.dist-info/RECORD
